sqlalchemy_crud_tx/__init__.py
sqlalchemy_crud_tx/core.py
sqlalchemy_crud_tx/crud.py
sqlalchemy_crud_tx/query.py
sqlalchemy_crud_tx/status.py
sqlalchemy_crud_tx/transaction.py
sqlalchemy_crud_tx/types.py
sqlalchemy_crud_tx-0.3.0.dist-info/licenses/LICENSE
sqlalchemy_crud_tx-0.3.0.dist-info/METADATA
sqlalchemy_crud_tx-0.3.0.dist-info/WHEEL
sqlalchemy_crud_tx-0.3.0.dist-info/top_level.txt
sqlalchemy_crud_tx-0.3.0.dist-info/RECORD
