Metadata-Version: 2.4
Name: sqlalchemy-crud-tx
Version: 0.3.0
Summary: Use SQLAlchemy in a Pythonic way.
Author: ZMKimu
License: MIT
Project-URL: Homepage, https://github.com/ZM-Kimu/sqlalchemy-crud-tx
Requires-Python: >=3.11
License-File: LICENSE
Requires-Dist: sqlalchemy>=1.4
Provides-Extra: flask
Requires-Dist: flask>=2.3; extra == "flask"
Requires-Dist: flask-sqlalchemy>=3.1; extra == "flask"
Dynamic: license-file
